rocksq-0.3.0.dist-info/METADATA
rocksq-0.3.0.dist-info/WHEEL
rocksq/rocksq.pyi
rocksq/blocking/__init__.py
rocksq/blocking/blocking.pyi
rocksq/py.typed
rocksq/nonblocking/nonblocking.pyi
rocksq/nonblocking/__init__.py
rocksq/__init__.py
rocksq/rocksq.pypy38-pp73-x86_64-linux-gnu.so
rocksq-0.3.0.dist-info/RECORD
