Metadata-Version: 2.1
Name: rocksq
Version: 0.3.0
Classifier: Programming Language :: Rust
Classifier: Programming Language :: Python :: Implementation :: CPython
Classifier: Programming Language :: Python :: Implementation :: PyPy
Summary: Rust persistent queue based on RocksDB with Python bindings
Keywords: database,queue,persistent,rocksdb,python
Home-Page: https://github.com/insight-platform/RocksQ
Author: Ivan Kudriavtsev <ivan.a.kudryavtsev@gmail.com>
Author-email: Ivan Kudriavtsev <ivan.a.kudryavtsev@gmail.com>
License: Apache-2.0
Requires-Python: >=3.8
Project-URL: Source Code, https://github.com/insight-platform/RocksQ
